yats/__init__.py
yats/__main__.py
yats/connector.py
yats/custom_datetime.py
yats/iterable_queue.py
yats/logging_helper.py
yats/profile.py
yats/request.py
yats/requests_holder.py
yats/serie.py
yats/sorted_element.py
yats/sorted_set.py
yats/tweet.py
yats/tweet_set.py
yats/twitter_request.py
yats/__pycache__/__init__.cpython-39.pyc
yats/__pycache__/request.cpython-39.pyc
yats-1.0.1.dist-info/LICENSE
yats-1.0.1.dist-info/METADATA
yats-1.0.1.dist-info/WHEEL
yats-1.0.1.dist-info/entry_points.txt
yats-1.0.1.dist-info/top_level.txt
yats-1.0.1.dist-info/RECORD
