Metadata-Version: 2.1
Name: yats
Version: 1.0.1
Summary: A fast lightweight Twitter scraper
Home-page: https://github.com/GaryOma/yats
Author: Gary SUBLET
Author-email: gary.sublet@hotmail.fr
License: MIT
Platform: UNKNOWN
Classifier: License :: OSI Approved :: MIT License
Classifier: Programming Language :: Python :: 3.6
Classifier: Programming Language :: Python :: 3.7
Classifier: Programming Language :: Python :: 3.8
License-File: LICENSE
